README.txt
plonetheme.python-configure.zcml
setup.cfg
setup.py
docs/HISTORY.txt
docs/INSTALL.txt
docs/LICENSE.GPL
docs/LICENSE.txt
plonetheme/__init__.py
plonetheme.python.egg-info/PKG-INFO
plonetheme.python.egg-info/SOURCES.txt
plonetheme.python.egg-info/dependency_links.txt
plonetheme.python.egg-info/entry_points.txt
plonetheme.python.egg-info/namespace_packages.txt
plonetheme.python.egg-info/not-zip-safe
plonetheme.python.egg-info/requires.txt
plonetheme.python.egg-info/top_level.txt
plonetheme/python/__init__.py
plonetheme/python/configure.zcml
plonetheme/python/profiles.zcml
plonetheme/python/setuphandlers.py
plonetheme/python/skins.zcml
plonetheme/python/tests.py
plonetheme/python/version.txt
plonetheme/python/browser/__init__.py
plonetheme/python/browser/configure.zcml
plonetheme/python/browser/interfaces.py
plonetheme/python/browser/viewlet.pt
plonetheme/python/browser/viewlets.py
plonetheme/python/browser/images/README.txt
plonetheme/python/browser/images/bg.png
plonetheme/python/browser/images/bullet.gif
plonetheme/python/browser/images/button-on-bg.png
plonetheme/python/browser/images/nav-off-bg.png
plonetheme/python/browser/images/nav-on-bg.png
plonetheme/python/browser/stylesheets/README.txt
plonetheme/python/browser/stylesheets/main.css
plonetheme/python/browser/viewlets/font_size_changer.pt
plonetheme/python/profiles/default/cssregistry.xml
plonetheme/python/profiles/default/import_steps.xml
plonetheme/python/profiles/default/jsregistry.xml
plonetheme/python/profiles/default/plonetheme.python_various.txt
plonetheme/python/profiles/default/skins.xml
plonetheme/python/profiles/default/viewlets.xml
plonetheme/python/skins/plonetheme_python_custom_images/CONTENT.txt
plonetheme/python/skins/plonetheme_python_custom_images/logo.jpg
plonetheme/python/skins/plonetheme_python_custom_templates/CONTENT.txt
plonetheme/python/skins/plonetheme_python_styles/CONTENT.txt
plonetheme/python/skins/plonetheme_python_styles/base.css.dtml
plonetheme/python/skins/plonetheme_python_styles/base_properties.props
plonetheme/python/skins/plonetheme_python_styles/portlets.css.dtml
plonetheme/python/skins/plonetheme_python_styles/public.css.dtml
