Metadata-Version: 1.0
Name: plonetheme.python
Version: 0.1dev-r57597
Summary: An installable theme for Plone 3.0.
Home-page: www.speedbreeze.com
Author: Jonathan Wilde
Author-email: product-developers@lists.plone.org
License: GPL
Keywords: web zope plone theme
Platform: UNKNOWN
Classifier: Framework :: Plone
Classifier: Framework :: Zope2
Classifier: Framework :: Zope3
Classifier: Programming Language :: Python
Classifier: Topic :: Software Development :: Libraries :: Python Modules
